{
 "meta": {
  "date": "2026-07-14T18:08:46Z",
  "git_revision": "2023c20562a0a5cc1d83a097631cc0566849b029"
 },
    "results": [
        {
            "title": "assembly_kernels__continuous_lagrange",
            "name": "2d__laplace__p1",
            "unit": "op",
            "batch": 1,
            "complexityN": -1,
            "epochs": 5,
            "clockResolution": 2e-08,
            "clockResolutionMultiple": 1000,
            "maxEpochTime": 0.1,
            "minEpochTime": 0.001,
            "minEpochIterations": 1,
            "epochIterations": 0,
            "warmup": 1,
            "relative": 0,
            "median(elapsed)": 0.082190701,
            "medianAbsolutePercentError(elapsed)": 0.00196826141739746,
            "median(instructions)": 0,
            "medianAbsolutePercentError(instructions)": 0,
            "median(cpucycles)": 0,
            "median(contextswitches)": 0,
            "median(pagefaults)": 0,
            "median(branchinstructions)": 0,
            "median(branchmisses)": 0,
            "totalTime": 0.418144946,
            "measurements": [
                {
                    "iterations": 1,
                    "elapsed": 0.082190701,
                    "pagefaults": 0,
                    "cpucycles": 0,
                    "contextswitches": 0,
                    "instructions": 0,
                    "branchinstructions": 0,
                    "branchmisses": 0
                },
                {
                    "iterations": 1,
                    "elapsed": 0.082029246,
                    "pagefaults": 0,
                    "cpucycles": 0,
                    "contextswitches": 0,
                    "instructions": 0,
                    "branchinstructions": 0,
                    "branchmisses": 0
                },
                {
                    "iterations": 1,
                    "elapsed": 0.082168109,
                    "pagefaults": 0,
                    "cpucycles": 0,
                    "contextswitches": 0,
                    "instructions": 0,
                    "branchinstructions": 0,
                    "branchmisses": 0
                },
                {
                    "iterations": 1,
                    "elapsed": 0.087004245,
                    "pagefaults": 0,
                    "cpucycles": 0,
                    "contextswitches": 0,
                    "instructions": 0,
                    "branchinstructions": 0,
                    "branchmisses": 0
                },
                {
                    "iterations": 1,
                    "elapsed": 0.084752645,
                    "pagefaults": 0,
                    "cpucycles": 0,
                    "contextswitches": 0,
                    "instructions": 0,
                    "branchinstructions": 0,
                    "branchmisses": 0
                }
            ]
        },
        {
            "title": "assembly_kernels__continuous_lagrange",
            "name": "2d__product__p1",
            "unit": "op",
            "batch": 1,
            "complexityN": -1,
            "epochs": 5,
            "clockResolution": 2e-08,
            "clockResolutionMultiple": 1000,
            "maxEpochTime": 0.1,
            "minEpochTime": 0.001,
            "minEpochIterations": 1,
            "epochIterations": 0,
            "warmup": 1,
            "relative": 0,
            "median(elapsed)": 0.080343142,
            "medianAbsolutePercentError(elapsed)": 0.00162361650850039,
            "median(instructions)": 0,
            "medianAbsolutePercentError(instructions)": 0,
            "median(cpucycles)": 0,
            "median(contextswitches)": 0,
            "median(pagefaults)": 0,
            "median(branchinstructions)": 0,
            "median(branchmisses)": 0,
            "totalTime": 0.401771844,
            "measurements": [
                {
                    "iterations": 1,
                    "elapsed": 0.080440134,
                    "pagefaults": 0,
                    "cpucycles": 0,
                    "contextswitches": 0,
                    "instructions": 0,
                    "branchinstructions": 0,
                    "branchmisses": 0
                },
                {
                    "iterations": 1,
                    "elapsed": 0.080187328,
                    "pagefaults": 0,
                    "cpucycles": 0,
                    "contextswitches": 0,
                    "instructions": 0,
                    "branchinstructions": 0,
                    "branchmisses": 0
                },
                {
                    "iterations": 1,
                    "elapsed": 0.080588333,
                    "pagefaults": 0,
                    "cpucycles": 0,
                    "contextswitches": 0,
                    "instructions": 0,
                    "branchinstructions": 0,
                    "branchmisses": 0
                },
                {
                    "iterations": 1,
                    "elapsed": 0.080212907,
                    "pagefaults": 0,
                    "cpucycles": 0,
                    "contextswitches": 0,
                    "instructions": 0,
                    "branchinstructions": 0,
                    "branchmisses": 0
                },
                {
                    "iterations": 1,
                    "elapsed": 0.080343142,
                    "pagefaults": 0,
                    "cpucycles": 0,
                    "contextswitches": 0,
                    "instructions": 0,
                    "branchinstructions": 0,
                    "branchmisses": 0
                }
            ]
        },
        {
            "title": "assembly_kernels__continuous_lagrange",
            "name": "2d__laplace__p2",
            "unit": "op",
            "batch": 1,
            "complexityN": -1,
            "epochs": 5,
            "clockResolution": 2e-08,
            "clockResolutionMultiple": 1000,
            "maxEpochTime": 0.1,
            "minEpochTime": 0.001,
            "minEpochIterations": 1,
            "epochIterations": 0,
            "warmup": 1,
            "relative": 0,
            "median(elapsed)": 1.298085085,
            "medianAbsolutePercentError(elapsed)": 0.000471806444143992,
            "median(instructions)": 0,
            "medianAbsolutePercentError(instructions)": 0,
            "median(cpucycles)": 0,
            "median(contextswitches)": 0,
            "median(pagefaults)": 0,
            "median(branchinstructions)": 0,
            "median(branchmisses)": 0,
            "totalTime": 6.492696617,
            "measurements": [
                {
                    "iterations": 1,
                    "elapsed": 1.30126675,
                    "pagefaults": 0,
                    "cpucycles": 0,
                    "contextswitches": 0,
                    "instructions": 0,
                    "branchinstructions": 0,
                    "branchmisses": 0
                },
                {
                    "iterations": 1,
                    "elapsed": 1.298085085,
                    "pagefaults": 0,
                    "cpucycles": 0,
                    "contextswitches": 0,
                    "instructions": 0,
                    "branchinstructions": 0,
                    "branchmisses": 0
                },
                {
                    "iterations": 1,
                    "elapsed": 1.298697819,
                    "pagefaults": 0,
                    "cpucycles": 0,
                    "contextswitches": 0,
                    "instructions": 0,
                    "branchinstructions": 0,
                    "branchmisses": 0
                },
                {
                    "iterations": 1,
                    "elapsed": 1.296854879,
                    "pagefaults": 0,
                    "cpucycles": 0,
                    "contextswitches": 0,
                    "instructions": 0,
                    "branchinstructions": 0,
                    "branchmisses": 0
                },
                {
                    "iterations": 1,
                    "elapsed": 1.297792084,
                    "pagefaults": 0,
                    "cpucycles": 0,
                    "contextswitches": 0,
                    "instructions": 0,
                    "branchinstructions": 0,
                    "branchmisses": 0
                }
            ]
        },
        {
            "title": "assembly_kernels__continuous_lagrange",
            "name": "2d__product__p2",
            "unit": "op",
            "batch": 1,
            "complexityN": -1,
            "epochs": 5,
            "clockResolution": 2e-08,
            "clockResolutionMultiple": 1000,
            "maxEpochTime": 0.1,
            "minEpochTime": 0.001,
            "minEpochIterations": 1,
            "epochIterations": 0,
            "warmup": 1,
            "relative": 0,
            "median(elapsed)": 1.292656738,
            "medianAbsolutePercentError(elapsed)": 0.000918931939698589,
            "median(instructions)": 0,
            "medianAbsolutePercentError(instructions)": 0,
            "median(cpucycles)": 0,
            "median(contextswitches)": 0,
            "median(pagefaults)": 0,
            "median(branchinstructions)": 0,
            "median(branchmisses)": 0,
            "totalTime": 6.484363495,
            "measurements": [
                {
                    "iterations": 1,
                    "elapsed": 1.292106035,
                    "pagefaults": 0,
                    "cpucycles": 0,
                    "contextswitches": 0,
                    "instructions": 0,
                    "branchinstructions": 0,
                    "branchmisses": 0
                },
                {
                    "iterations": 1,
                    "elapsed": 1.309552303,
                    "pagefaults": 0,
                    "cpucycles": 0,
                    "contextswitches": 0,
                    "instructions": 0,
                    "branchinstructions": 0,
                    "branchmisses": 0
                },
                {
                    "iterations": 1,
                    "elapsed": 1.292656738,
                    "pagefaults": 0,
                    "cpucycles": 0,
                    "contextswitches": 0,
                    "instructions": 0,
                    "branchinstructions": 0,
                    "branchmisses": 0
                },
                {
                    "iterations": 1,
                    "elapsed": 1.291469965,
                    "pagefaults": 0,
                    "cpucycles": 0,
                    "contextswitches": 0,
                    "instructions": 0,
                    "branchinstructions": 0,
                    "branchmisses": 0
                },
                {
                    "iterations": 1,
                    "elapsed": 1.298578454,
                    "pagefaults": 0,
                    "cpucycles": 0,
                    "contextswitches": 0,
                    "instructions": 0,
                    "branchinstructions": 0,
                    "branchmisses": 0
                }
            ]
        },
        {
            "title": "assembly_kernels__continuous_lagrange",
            "name": "2d__laplace__p3",
            "unit": "op",
            "batch": 1,
            "complexityN": -1,
            "epochs": 5,
            "clockResolution": 2e-08,
            "clockResolutionMultiple": 1000,
            "maxEpochTime": 0.1,
            "minEpochTime": 0.001,
            "minEpochIterations": 1,
            "epochIterations": 0,
            "warmup": 1,
            "relative": 0,
            "median(elapsed)": 7.006275095,
            "medianAbsolutePercentError(elapsed)": 0.000187119582404438,
            "median(instructions)": 0,
            "medianAbsolutePercentError(instructions)": 0,
            "median(cpucycles)": 0,
            "median(contextswitches)": 0,
            "median(pagefaults)": 0,
            "median(branchinstructions)": 0,
            "median(branchmisses)": 0,
            "totalTime": 35.039607063,
            "measurements": [
                {
                    "iterations": 1,
                    "elapsed": 7.004964329,
                    "pagefaults": 0,
                    "cpucycles": 0,
                    "contextswitches": 0,
                    "instructions": 0,
                    "branchinstructions": 0,
                    "branchmisses": 0
                },
                {
                    "iterations": 1,
                    "elapsed": 7.022374079,
                    "pagefaults": 0,
                    "cpucycles": 0,
                    "contextswitches": 0,
                    "instructions": 0,
                    "branchinstructions": 0,
                    "branchmisses": 0
                },
                {
                    "iterations": 1,
                    "elapsed": 6.998470559,
                    "pagefaults": 0,
                    "cpucycles": 0,
                    "contextswitches": 0,
                    "instructions": 0,
                    "branchinstructions": 0,
                    "branchmisses": 0
                },
                {
                    "iterations": 1,
                    "elapsed": 7.006275095,
                    "pagefaults": 0,
                    "cpucycles": 0,
                    "contextswitches": 0,
                    "instructions": 0,
                    "branchinstructions": 0,
                    "branchmisses": 0
                },
                {
                    "iterations": 1,
                    "elapsed": 7.007523001,
                    "pagefaults": 0,
                    "cpucycles": 0,
                    "contextswitches": 0,
                    "instructions": 0,
                    "branchinstructions": 0,
                    "branchmisses": 0
                }
            ]
        },
        {
            "title": "assembly_kernels__continuous_lagrange",
            "name": "2d__product__p3",
            "unit": "op",
            "batch": 1,
            "complexityN": -1,
            "epochs": 5,
            "clockResolution": 2e-08,
            "clockResolutionMultiple": 1000,
            "maxEpochTime": 0.1,
            "minEpochTime": 0.001,
            "minEpochIterations": 1,
            "epochIterations": 0,
            "warmup": 1,
            "relative": 0,
            "median(elapsed)": 6.995060956,
            "medianAbsolutePercentError(elapsed)": 0.000954963760574214,
            "median(instructions)": 0,
            "medianAbsolutePercentError(instructions)": 0,
            "median(cpucycles)": 0,
            "median(contextswitches)": 0,
            "median(pagefaults)": 0,
            "median(branchinstructions)": 0,
            "median(branchmisses)": 0,
            "totalTime": 34.997480565,
            "measurements": [
                {
                    "iterations": 1,
                    "elapsed": 7.001747371,
                    "pagefaults": 0,
                    "cpucycles": 0,
                    "contextswitches": 0,
                    "instructions": 0,
                    "branchinstructions": 0,
                    "branchmisses": 0
                },
                {
                    "iterations": 1,
                    "elapsed": 6.995060956,
                    "pagefaults": 0,
                    "cpucycles": 0,
                    "contextswitches": 0,
                    "instructions": 0,
                    "branchinstructions": 0,
                    "branchmisses": 0
                },
                {
                    "iterations": 1,
                    "elapsed": 6.990027384,
                    "pagefaults": 0,
                    "cpucycles": 0,
                    "contextswitches": 0,
                    "instructions": 0,
                    "branchinstructions": 0,
                    "branchmisses": 0
                },
                {
                    "iterations": 1,
                    "elapsed": 6.984321625,
                    "pagefaults": 0,
                    "cpucycles": 0,
                    "contextswitches": 0,
                    "instructions": 0,
                    "branchinstructions": 0,
                    "branchmisses": 0
                },
                {
                    "iterations": 1,
                    "elapsed": 7.026323229,
                    "pagefaults": 0,
                    "cpucycles": 0,
                    "contextswitches": 0,
                    "instructions": 0,
                    "branchinstructions": 0,
                    "branchmisses": 0
                }
            ]
        },
        {
            "title": "assembly_kernels__continuous_lagrange",
            "name": "3d__laplace__p1",
            "unit": "op",
            "batch": 1,
            "complexityN": -1,
            "epochs": 5,
            "clockResolution": 2e-08,
            "clockResolutionMultiple": 1000,
            "maxEpochTime": 0.1,
            "minEpochTime": 0.001,
            "minEpochIterations": 1,
            "epochIterations": 0,
            "warmup": 1,
            "relative": 0,
            "median(elapsed)": 0.036895638,
            "medianAbsolutePercentError(elapsed)": 0.000655365893573551,
            "median(instructions)": 0,
            "medianAbsolutePercentError(instructions)": 0,
            "median(cpucycles)": 0,
            "median(contextswitches)": 0,
            "median(pagefaults)": 0,
            "median(branchinstructions)": 0,
            "median(branchmisses)": 0,
            "totalTime": 0.184841975,
            "measurements": [
                {
                    "iterations": 1,
                    "elapsed": 0.036746818,
                    "pagefaults": 0,
                    "cpucycles": 0,
                    "contextswitches": 0,
                    "instructions": 0,
                    "branchinstructions": 0,
                    "branchmisses": 0
                },
                {
                    "iterations": 1,
                    "elapsed": 0.036883014,
                    "pagefaults": 0,
                    "cpucycles": 0,
                    "contextswitches": 0,
                    "instructions": 0,
                    "branchinstructions": 0,
                    "branchmisses": 0
                },
                {
                    "iterations": 1,
                    "elapsed": 0.036919834,
                    "pagefaults": 0,
                    "cpucycles": 0,
                    "contextswitches": 0,
                    "instructions": 0,
                    "branchinstructions": 0,
                    "branchmisses": 0
                },
                {
                    "iterations": 1,
                    "elapsed": 0.037396671,
                    "pagefaults": 0,
                    "cpucycles": 0,
                    "contextswitches": 0,
                    "instructions": 0,
                    "branchinstructions": 0,
                    "branchmisses": 0
                },
                {
                    "iterations": 1,
                    "elapsed": 0.036895638,
                    "pagefaults": 0,
                    "cpucycles": 0,
                    "contextswitches": 0,
                    "instructions": 0,
                    "branchinstructions": 0,
                    "branchmisses": 0
                }
            ]
        },
        {
            "title": "assembly_kernels__continuous_lagrange",
            "name": "3d__product__p1",
            "unit": "op",
            "batch": 1,
            "complexityN": -1,
            "epochs": 5,
            "clockResolution": 2e-08,
            "clockResolutionMultiple": 1000,
            "maxEpochTime": 0.1,
            "minEpochTime": 0.001,
            "minEpochIterations": 1,
            "epochIterations": 0,
            "warmup": 1,
            "relative": 0,
            "median(elapsed)": 0.034578205,
            "medianAbsolutePercentError(elapsed)": 0.000625930087110822,
            "median(instructions)": 0,
            "medianAbsolutePercentError(instructions)": 0,
            "median(cpucycles)": 0,
            "median(contextswitches)": 0,
            "median(pagefaults)": 0,
            "median(branchinstructions)": 0,
            "median(branchmisses)": 0,
            "totalTime": 0.173660104,
            "measurements": [
                {
                    "iterations": 1,
                    "elapsed": 0.034930187,
                    "pagefaults": 0,
                    "cpucycles": 0,
                    "contextswitches": 0,
                    "instructions": 0,
                    "branchinstructions": 0,
                    "branchmisses": 0
                },
                {
                    "iterations": 1,
                    "elapsed": 0.034578205,
                    "pagefaults": 0,
                    "cpucycles": 0,
                    "contextswitches": 0,
                    "instructions": 0,
                    "branchinstructions": 0,
                    "branchmisses": 0
                },
                {
                    "iterations": 1,
                    "elapsed": 0.034556575,
                    "pagefaults": 0,
                    "cpucycles": 0,
                    "contextswitches": 0,
                    "instructions": 0,
                    "branchinstructions": 0,
                    "branchmisses": 0
                },
                {
                    "iterations": 1,
                    "elapsed": 0.034567385,
                    "pagefaults": 0,
                    "cpucycles": 0,
                    "contextswitches": 0,
                    "instructions": 0,
                    "branchinstructions": 0,
                    "branchmisses": 0
                },
                {
                    "iterations": 1,
                    "elapsed": 0.035027752,
                    "pagefaults": 0,
                    "cpucycles": 0,
                    "contextswitches": 0,
                    "instructions": 0,
                    "branchinstructions": 0,
                    "branchmisses": 0
                }
            ]
        },
        {
            "title": "assembly_kernels__continuous_lagrange",
            "name": "3d__laplace__p2",
            "unit": "op",
            "batch": 1,
            "complexityN": -1,
            "epochs": 5,
            "clockResolution": 2e-08,
            "clockResolutionMultiple": 1000,
            "maxEpochTime": 0.1,
            "minEpochTime": 0.001,
            "minEpochIterations": 1,
            "epochIterations": 0,
            "warmup": 1,
            "relative": 0,
            "median(elapsed)": 1.649223908,
            "medianAbsolutePercentError(elapsed)": 0.000702630623338531,
            "median(instructions)": 0,
            "medianAbsolutePercentError(instructions)": 0,
            "median(cpucycles)": 0,
            "median(contextswitches)": 0,
            "median(pagefaults)": 0,
            "median(branchinstructions)": 0,
            "median(branchmisses)": 0,
            "totalTime": 8.24610574,
            "measurements": [
                {
                    "iterations": 1,
                    "elapsed": 1.649223908,
                    "pagefaults": 0,
                    "cpucycles": 0,
                    "contextswitches": 0,
                    "instructions": 0,
                    "branchinstructions": 0,
                    "branchmisses": 0
                },
                {
                    "iterations": 1,
                    "elapsed": 1.646368722,
                    "pagefaults": 0,
                    "cpucycles": 0,
                    "contextswitches": 0,
                    "instructions": 0,
                    "branchinstructions": 0,
                    "branchmisses": 0
                },
                {
                    "iterations": 1,
                    "elapsed": 1.648107671,
                    "pagefaults": 0,
                    "cpucycles": 0,
                    "contextswitches": 0,
                    "instructions": 0,
                    "branchinstructions": 0,
                    "branchmisses": 0
                },
                {
                    "iterations": 1,
                    "elapsed": 1.650383518,
                    "pagefaults": 0,
                    "cpucycles": 0,
                    "contextswitches": 0,
                    "instructions": 0,
                    "branchinstructions": 0,
                    "branchmisses": 0
                },
                {
                    "iterations": 1,
                    "elapsed": 1.652021921,
                    "pagefaults": 0,
                    "cpucycles": 0,
                    "contextswitches": 0,
                    "instructions": 0,
                    "branchinstructions": 0,
                    "branchmisses": 0
                }
            ]
        },
        {
            "title": "assembly_kernels__continuous_lagrange",
            "name": "3d__product__p2",
            "unit": "op",
            "batch": 1,
            "complexityN": -1,
            "epochs": 5,
            "clockResolution": 2e-08,
            "clockResolutionMultiple": 1000,
            "maxEpochTime": 0.1,
            "minEpochTime": 0.001,
            "minEpochIterations": 1,
            "epochIterations": 0,
            "warmup": 1,
            "relative": 0,
            "median(elapsed)": 1.589128199,
            "medianAbsolutePercentError(elapsed)": 0.000959191663675706,
            "median(instructions)": 0,
            "medianAbsolutePercentError(instructions)": 0,
            "median(cpucycles)": 0,
            "median(contextswitches)": 0,
            "median(pagefaults)": 0,
            "median(branchinstructions)": 0,
            "median(branchmisses)": 0,
            "totalTime": 7.940344143,
            "measurements": [
                {
                    "iterations": 1,
                    "elapsed": 1.581645144,
                    "pagefaults": 0,
                    "cpucycles": 0,
                    "contextswitches": 0,
                    "instructions": 0,
                    "branchinstructions": 0,
                    "branchmisses": 0
                },
                {
                    "iterations": 1,
                    "elapsed": 1.591220947,
                    "pagefaults": 0,
                    "cpucycles": 0,
                    "contextswitches": 0,
                    "instructions": 0,
                    "branchinstructions": 0,
                    "branchmisses": 0
                },
                {
                    "iterations": 1,
                    "elapsed": 1.590653941,
                    "pagefaults": 0,
                    "cpucycles": 0,
                    "contextswitches": 0,
                    "instructions": 0,
                    "branchinstructions": 0,
                    "branchmisses": 0
                },
                {
                    "iterations": 1,
                    "elapsed": 1.589128199,
                    "pagefaults": 0,
                    "cpucycles": 0,
                    "contextswitches": 0,
                    "instructions": 0,
                    "branchinstructions": 0,
                    "branchmisses": 0
                },
                {
                    "iterations": 1,
                    "elapsed": 1.587695912,
                    "pagefaults": 0,
                    "cpucycles": 0,
                    "contextswitches": 0,
                    "instructions": 0,
                    "branchinstructions": 0,
                    "branchmisses": 0
                }
            ]
        }
    ]
}