{
 "meta": {
  "date": "2026-06-13T19:34:35Z",
  "git_revision": "2ea339a869d805140b3ec8eb76156710b2bda47b"
 },
    "results": [
        {
            "title": "burgers__1d__explicit__fv",
            "name": "explicit_euler__upwind",
            "unit": "op",
            "batch": 1,
            "complexityN": -1,
            "epochs": 3,
            "clockResolution": 2e-08,
            "clockResolutionMultiple": 1000,
            "maxEpochTime": 0.1,
            "minEpochTime": 0.001,
            "minEpochIterations": 1,
            "epochIterations": 0,
            "warmup": 0,
            "relative": 0,
            "median(elapsed)": 4.147931204,
            "medianAbsolutePercentError(elapsed)": 7.57774902966018e-05,
            "median(instructions)": 0,
            "medianAbsolutePercentError(instructions)": 0,
            "median(cpucycles)": 0,
            "median(contextswitches)": 0,
            "median(pagefaults)": 0,
            "median(branchinstructions)": 0,
            "median(branchmisses)": 0,
            "totalTime": 12.446805752,
            "measurements": [
                {
                    "iterations": 1,
                    "elapsed": 4.15125764,
                    "pagefaults": 0,
                    "cpucycles": 0,
                    "contextswitches": 0,
                    "instructions": 0,
                    "branchinstructions": 0,
                    "branchmisses": 0
                },
                {
                    "iterations": 1,
                    "elapsed": 4.147616908,
                    "pagefaults": 0,
                    "cpucycles": 0,
                    "contextswitches": 0,
                    "instructions": 0,
                    "branchinstructions": 0,
                    "branchmisses": 0
                },
                {
                    "iterations": 1,
                    "elapsed": 4.147931204,
                    "pagefaults": 0,
                    "cpucycles": 0,
                    "contextswitches": 0,
                    "instructions": 0,
                    "branchinstructions": 0,
                    "branchmisses": 0
                }
            ]
        }
    ]
}